utils/__init__.py
utils/argparse.py
utils/config.py
utils/configurable.py
utils/contextlib.py
utils/exceptions.py
utils/functools.py
utils/io.py
utils/itertools.py
utils/logging.py
utils/npf.py
utils/pd.py
utils/plot.py
utils/pprint.py
utils/timeit.py
utils/bpd/__init__.py
utils/bpd/array.py
utils/bpd/dataframe.py
utils/bpd/parsing.py
utils/np/__init__.py
utils/np/core.py
utils/np/stats.py
utils/pt/__init__.py
utils/pt/core.py
utils/sp/__init__.py
utils/sp/stats.py
hyc_utils-0.5.33.dist-info/LICENSE
hyc_utils-0.5.33.dist-info/METADATA
hyc_utils-0.5.33.dist-info/WHEEL
hyc_utils-0.5.33.dist-info/top_level.txt
hyc_utils-0.5.33.dist-info/RECORD
