Metadata-Version: 2.1
Name: hyc-utils
Version: 0.5.33
Summary: Commonly used tools across my own personal projects
License-File: LICENSE
Requires-Dist: numpy
Requires-Dist: matplotlib
Requires-Dist: statsmodels
Requires-Dist: torch
Requires-Dist: tomli
Requires-Dist: h5py
Requires-Dist: pandas
Requires-Dist: tables
Requires-Dist: tqdm
Requires-Dist: mat73
Requires-Dist: platformdirs
Provides-Extra: test
Requires-Dist: pytest ; extra == 'test'
Requires-Dist: scipy ; extra == 'test'
